geosub/__init__.py
geosub/geolookup.py
geosub/sublookup.py
geosub/data/__init__.py
geosub/data/geonames_all_countries_sorted.tsv
geosub-0.1.2a0.dist-info/LICENSE
geosub-0.1.2a0.dist-info/METADATA
geosub-0.1.2a0.dist-info/WHEEL
geosub-0.1.2a0.dist-info/top_level.txt
geosub-0.1.2a0.dist-info/RECORD
