Metadata-Version: 2.1
Name: geosub
Version: 0.1.2a0
Summary: Lookup ISO 3166-2 geographic subdivisions from postal and country codes, using GeoNames and pycountry.
License: ## License for included geographic data
Project-URL: Source, https://github.com/dmayo3/geosub
Project-URL: Docs, http://geosub.readthedocs.io/
Keywords: geo,country,subdivision,postal code,ISO 3166-1,ISO 3166-2
Classifier: Development Status :: 3 - Alpha
Classifier: Natural Language :: English
Classifier: Operating System :: OS Independent
Classifier: Intended Audience :: Developers
Classifier: Programming Language :: Python
Classifier: Programming Language :: Python :: 3
Classifier: Programming Language :: Python :: 3.9
Classifier: Programming Language :: Python :: 3.10
Classifier: Programming Language :: Python :: 3.11
Classifier: Programming Language :: Python :: 3.12
Classifier: Programming Language :: Python :: 3 :: Only
Classifier: Programming Language :: Python :: Implementation :: CPython
Classifier: Topic :: Software Development :: Libraries
Classifier: Topic :: Utilities
Classifier: Typing :: Typed
Requires-Python: >=3.9
License-File: LICENSE
Requires-Dist: pycountry~=24.6
Provides-Extra: docs
Requires-Dist: sphinx-rtd-theme>=1.2.0; extra == "docs"
